{
  "processed_guids": [
    "10f5b05a-3f65-4473-8499-a049c9de542d",
    "a10f7c49-6a6d-4a75-bd9f-304f9b19262e",
    "97a38141-1f84-4d15-b603-8ae1470ec10d",
    "50250ac2-e0f8-421e-8bc5-2e1addd6c05c",
    "7b232808-ac5a-4d76-a0a8-4ad48e393f29",
    "9e925dc6-6230-45d8-b2ee-311a14c26673",
    "7bd5facf-39ec-4643-a0ed-f76a9fbae23f"
  ],
  "clips": [
    {
      "guid": "10f5b05a-3f65-4473-8499-a049c9de542d",
      "title": "「日本人は集団主義」の嘘！〜 『空気という妖怪』の倒し方〜 #240",
      "pub_date": "Tue, 09 Jun 2026 21:30:00 GMT",
      "episode_url": "https://podcasters.spotify.com/pod/show/ningenradio/episodes/240-e3kdjhg",
      "audio_url": "https://anchor.fm/s/9bb1c5d8/podcast/play/121080816/https%3A%2F%2Fd3ctxlq1ktw2nl.cloudfront.net%2Fstaging%2F2026-5-6%2F16727168-b520-7e0a-d9ac-eee0c0e7067f.mp3",
      "clip_path": "/home/runner/work/xposting/xposting/clip_outputs/「日本人は集団主義」の嘘！〜_『空気という妖怪』の倒し方〜_#240_clip.mp4",
      "clip_filename": "「日本人は集団主義」の嘘！〜_『空気という妖怪』の倒し方〜_#240_clip.mp4",
      "clip_seconds": 15.0,
      "audio_duration_seconds": 1251.0,
      "clip_start_seconds": 458.109,
      "file_size_bytes": 945107,
      "created_at_unix": 1781114061
    },
    {
      "guid": "a10f7c49-6a6d-4a75-bd9f-304f9b19262e",
      "title": "脱「個人的には」！じゃぁどう言えばいい？ #241",
      "pub_date": "Sun, 14 Jun 2026 21:30:00 GMT",
      "episode_url": "https://podcasters.spotify.com/pod/show/ningenradio/episodes/241-e3kdk9f",
      "audio_url": "https://anchor.fm/s/9bb1c5d8/podcast/play/121081583/https%3A%2F%2Fd3ctxlq1ktw2nl.cloudfront.net%2Fstaging%2F2026-5-6%2F425611656-44100-2-abbefed198245.m4a",
      "clip_path": "/home/runner/work/xposting/xposting/clip_outputs/脱「個人的には」！じゃぁどう言えばいい？_#241_clip.mp4",
      "clip_filename": "脱「個人的には」！じゃぁどう言えばいい？_#241_clip.mp4",
      "clip_seconds": 15.0,
      "audio_duration_seconds": 477.755,
      "clip_start_seconds": 381.504,
      "file_size_bytes": 940896,
      "created_at_unix": 1781515485
    },
    {
      "guid": "97a38141-1f84-4d15-b603-8ae1470ec10d",
      "title": "間違えたら即退社！君の広告クイズ #242",
      "pub_date": "Tue, 16 Jun 2026 21:30:00 GMT",
      "episode_url": "https://podcasters.spotify.com/pod/show/ningenradio/episodes/242-e3kdjes",
      "audio_url": "https://anchor.fm/s/9bb1c5d8/podcast/play/121080732/https%3A%2F%2Fd3ctxlq1ktw2nl.cloudfront.net%2Fstaging%2F2026-5-6%2Fa2091067-7112-e181-4e65-bc254ed37a85.mp3",
      "clip_path": "/home/runner/work/xposting/xposting/clip_outputs/間違えたら即退社！君の広告クイズ_#242_clip.mp4",
      "clip_filename": "間違えたら即退社！君の広告クイズ_#242_clip.mp4",
      "clip_seconds": 15.0,
      "audio_duration_seconds": 2189.016,
      "clip_start_seconds": 471.672,
      "file_size_bytes": 954733,
      "created_at_unix": 1781685005
    },
    {
      "guid": "50250ac2-e0f8-421e-8bc5-2e1addd6c05c",
      "title": "そんなことある？先輩を飲みに誘う方法がわからない #243",
      "pub_date": "Sun, 21 Jun 2026 21:30:00 GMT",
      "episode_url": "https://podcasters.spotify.com/pod/show/ningenradio/episodes/243-e3l1plb",
      "audio_url": "https://anchor.fm/s/9bb1c5d8/podcast/play/121742443/https%3A%2F%2Fd3ctxlq1ktw2nl.cloudfront.net%2Fstaging%2F2026-5-20%2F426495131-44100-2-67385a3962ab5.m4a",
      "clip_path": "/home/runner/work/xposting/xposting/clip_outputs/そんなことある？先輩を飲みに誘う方法がわからない_#243_clip.mp4",
      "clip_filename": "そんなことある？先輩を飲みに誘う方法がわからない_#243_clip.mp4",
      "clip_seconds": 15.0,
      "audio_duration_seconds": 587.29,
      "clip_start_seconds": 417.619,
      "file_size_bytes": 940142,
      "created_at_unix": 1782119529
    },
    {
      "guid": "7b232808-ac5a-4d76-a0a8-4ad48e393f29",
      "title": "実在したヤバい広告10連発！君の広告クイズいよいよクライマックス #244",
      "pub_date": "Tue, 23 Jun 2026 21:30:00 GMT",
      "episode_url": "https://podcasters.spotify.com/pod/show/ningenradio/episodes/10-244-e3l1pt7",
      "audio_url": "https://anchor.fm/s/9bb1c5d8/podcast/play/121742695/https%3A%2F%2Fd3ctxlq1ktw2nl.cloudfront.net%2Fstaging%2F2026-5-20%2Fab586bda-c2c8-b972-81c4-8cf582abb7b2.mp3",
      "clip_path": "/home/runner/work/xposting/xposting/clip_outputs/実在したヤバい広告10連発！君の広告クイズいよいよクライマックス_#244_clip.mp4",
      "clip_filename": "実在したヤバい広告10連発！君の広告クイズいよいよクライマックス_#244_clip.mp4",
      "clip_seconds": 15.0,
      "audio_duration_seconds": 1657.248,
      "clip_start_seconds": 311.935,
      "file_size_bytes": 962413,
      "created_at_unix": 1782283834
    },
    {
      "guid": "9e925dc6-6230-45d8-b2ee-311a14c26673",
      "title": "説明のコツ、伝わる人が使う3つの基本技術 #245",
      "pub_date": "Sun, 28 Jun 2026 21:30:00 GMT",
      "episode_url": "https://podcasters.spotify.com/pod/show/ningenradio/episodes/3-245-e3lbj1s",
      "audio_url": "https://anchor.fm/s/9bb1c5d8/podcast/play/122063356/https%3A%2F%2Fd3ctxlq1ktw2nl.cloudfront.net%2Fstaging%2F2026-5-27%2F426925447-44100-2-90ae52402f0d.m4a",
      "clip_path": "/home/runner/work/xposting/xposting/clip_outputs/説明のコツ、伝わる人が使う3つの基本技術_#245_clip.mp4",
      "clip_filename": "説明のコツ、伝わる人が使う3つの基本技術_#245_clip.mp4",
      "clip_seconds": 15.0,
      "audio_duration_seconds": 619.576,
      "clip_start_seconds": 459.325,
      "file_size_bytes": 949654,
      "created_at_unix": 1782720849
    },
    {
      "guid": "7bd5facf-39ec-4643-a0ed-f76a9fbae23f",
      "title": "決定版3C分析！ 〜「企業参謀」勝ち筋を見つける思考法 #246",
      "pub_date": "Tue, 30 Jun 2026 21:30:00 GMT",
      "episode_url": "https://podcasters.spotify.com/pod/show/ningenradio/episodes/3C--246-e3lbj8g",
      "audio_url": "https://anchor.fm/s/9bb1c5d8/podcast/play/122063568/https%3A%2F%2Fd3ctxlq1ktw2nl.cloudfront.net%2Fstaging%2F2026-5-27%2Fc5e98105-fe31-76f0-1920-897d8a519488.mp3",
      "clip_path": "/home/runner/work/xposting/xposting/clip_outputs/決定版3C分析！_〜「企業参謀」勝ち筋を見つける思考法_#246_clip.mp4",
      "clip_filename": "決定版3C分析！_〜「企業参謀」勝ち筋を見つける思考法_#246_clip.mp4",
      "clip_seconds": 15.0,
      "audio_duration_seconds": 1571.304,
      "clip_start_seconds": 1351.537,
      "file_size_bytes": 947189,
      "created_at_unix": 1782890008
    }
  ],
  "latest_clip": {
    "guid": "7bd5facf-39ec-4643-a0ed-f76a9fbae23f",
    "title": "決定版3C分析！ 〜「企業参謀」勝ち筋を見つける思考法 #246",
    "pub_date": "Tue, 30 Jun 2026 21:30:00 GMT",
    "episode_url": "https://podcasters.spotify.com/pod/show/ningenradio/episodes/3C--246-e3lbj8g",
    "audio_url": "https://anchor.fm/s/9bb1c5d8/podcast/play/122063568/https%3A%2F%2Fd3ctxlq1ktw2nl.cloudfront.net%2Fstaging%2F2026-5-27%2Fc5e98105-fe31-76f0-1920-897d8a519488.mp3",
    "clip_path": "/home/runner/work/xposting/xposting/clip_outputs/決定版3C分析！_〜「企業参謀」勝ち筋を見つける思考法_#246_clip.mp4",
    "clip_filename": "決定版3C分析！_〜「企業参謀」勝ち筋を見つける思考法_#246_clip.mp4",
    "clip_seconds": 15.0,
    "audio_duration_seconds": 1571.304,
    "clip_start_seconds": 1351.537,
    "file_size_bytes": 947189,
    "created_at_unix": 1782890008
  }
}
